stemgraphic/__init__.py
stemgraphic/aliases.py
stemgraphic/alpha.py
stemgraphic/graphic.py
stemgraphic/grid.py
stemgraphic/helpers.py
stemgraphic/num.py
stemgraphic/stopwords.py
stemgraphic/text.py
stemgraphic-0.9.1.data/scripts/stem
stemgraphic-0.9.1.data/scripts/stem.bat
stemgraphic-0.9.1.dist-info/AUTHORS.md
stemgraphic-0.9.1.dist-info/LICENSE
stemgraphic-0.9.1.dist-info/LICENSE.txt
stemgraphic-0.9.1.dist-info/METADATA
stemgraphic-0.9.1.dist-info/WHEEL
stemgraphic-0.9.1.dist-info/top_level.txt
stemgraphic-0.9.1.dist-info/RECORD
