Metadata-Version: 2.1
Name: stemgraphic
Version: 0.9.1
Summary: Graphic and text stem-and-leaf plots
Home-page: http://github.com/dionresearch/stemgraphic
Author: Francois Dion
Author-email: francois.dion@gmail.com
License: MIT
Platform: UNKNOWN
Classifier: Programming Language :: Python :: 3
Classifier: License :: OSI Approved :: MIT License
Classifier: Operating System :: OS Independent
